security_audit_app/__init__.py
security_audit_app/main.py
security_audit_app/styles.tcss
security_audit_app/Nanum_Gothic/NanumGothic-Bold.ttf
security_audit_app/Nanum_Gothic/NanumGothic-ExtraBold.ttf
security_audit_app/Nanum_Gothic/NanumGothic-Regular.ttf
security_audit_app/Nanum_Gothic/OFL.txt
security_audit_app/config/data_for_report.csv
security_audit_app/config/error_code_table.json
security_audit_app/scripts/generate_audit_report.sh
security_audit_app/scripts/security_audit.sh
security_audit-0.2.6.dist-info/METADATA
security_audit-0.2.6.dist-info/WHEEL
security_audit-0.2.6.dist-info/entry_points.txt
security_audit-0.2.6.dist-info/top_level.txt
security_audit-0.2.6.dist-info/RECORD
