Metadata-Version: 2.4
Name: security_audit
Version: 0.2.6
Summary: A TUI application for automatic security auditing and report generation.
Author-email: KIM KIHYUN <bc2430@naver.com>
Requires-Python: >=3.8
Requires-Dist: textual>=6.6.0
Requires-Dist: textual-fspicker>=0.6.0
Requires-Dist: paramiko>=4.0.0
